    {
  "roles": {
    "defender": {
      "hp": 600,
      "attack": 30,
      "defense": 30,
      "attack_speed": 0.8,
      "mana_on_attack": 5,
      "mana_regen": 4,
      "color": "#4ade80"
    },
    "fighter": {
      "hp": 500,
      "attack": 40,
      "defense": 20,
      "attack_speed": 1.0,
      "mana_on_attack": 3,
      "mana_regen": 5,
      "color": "#f87171"
    },
    "duelist": {
      "hp": 450,
      "attack": 60,
      "defense": 15,
      "attack_speed": 1.2,
      "mana_on_attack": 5,
      "mana_regen": 6,
      "color": "#d97706"
    },
    "mage": {
      "hp": 400,
      "attack": 30,
      "defense": 10,
      "attack_speed": 0.9,
      "mana_on_attack": 7,
      "mana_regen": 8,
      "color": "#a78bfa"
    }
  }
}